lsip6/__init__.py
lsip6/__main__.py
lsip6-0.2.dist-info/LICENSE
lsip6-0.2.dist-info/METADATA
lsip6-0.2.dist-info/WHEEL
lsip6-0.2.dist-info/entry_points.txt
lsip6-0.2.dist-info/top_level.txt
lsip6-0.2.dist-info/RECORD
